{
  "n_states": 16,
  "pearson_pc_gap": {
    "r": -0.516,
    "p": 0.041
  },
  "pearson_rural_gap": {
    "r": 0.508,
    "p": 0.044
  },
  "rural_vs_urban": {
    "rural_states_n": 9,
    "rural_mean_gap": 5.27,
    "urban_states_n": 7,
    "urban_mean_gap": 4.21,
    "difference_pp": 1.05,
    "t": 2.293,
    "p": 0.038
  },
  "low_vs_high_pc_density": {
    "low_pc_n": 8,
    "low_pc_mean_gap": 5.0,
    "high_pc_n": 8,
    "high_pc_mean_gap": 4.61,
    "difference_pp": -0.39,
    "t": 0.74,
    "p": 0.472
  },
  "state_data": {
    "GA": {
      "pc_providers": 116,
      "rural_pct": 25,
      "racial_gap": 6.2,
      "wr": "active"
    },
    "FL": {
      "pc_providers": 2464,
      "rural_pct": 8,
      "racial_gap": 4.5,
      "wr": "pending"
    },
    "LA": {
      "pc_providers": 1140,
      "rural_pct": 27,
      "racial_gap": 6.6,
      "wr": "pending"
    },
    "OH": {
      "pc_providers": 2287,
      "rural_pct": 21,
      "racial_gap": 5.5,
      "wr": "pending"
    },
    "NC": {
      "pc_providers": 1932,
      "rural_pct": 33,
      "racial_gap": 4.3,
      "wr": "active"
    },
    "MI": {
      "pc_providers": 868,
      "rural_pct": 25,
      "racial_gap": 5.2,
      "wr": "blocked"
    },
    "TX": {
      "pc_providers": 3060,
      "rural_pct": 15,
      "racial_gap": 4.8,
      "wr": "pending"
    },
    "TN": {
      "pc_providers": 421,
      "rural_pct": 23,
      "racial_gap": 4.5,
      "wr": "pending"
    },
    "IN": {
      "pc_providers": 737,
      "rural_pct": 27,
      "racial_gap": 5.3,
      "wr": "active"
    },
    "WI": {
      "pc_providers": 936,
      "rural_pct": 29,
      "racial_gap": 5.5,
      "wr": "blocked"
    },
    "KY": {
      "pc_providers": 868,
      "rural_pct": 42,
      "racial_gap": 5.4,
      "wr": "blocked"
    },
    "AZ": {
      "pc_providers": 935,
      "rural_pct": 10,
      "racial_gap": 4.5,
      "wr": "pending"
    },
    "AR": {
      "pc_providers": 665,
      "rural_pct": 32,
      "racial_gap": 4.6,
      "wr": "terminated"
    },
    "CA": {
      "pc_providers": 3200,
      "rural_pct": 5,
      "racial_gap": 2.3,
      "wr": "none"
    },
    "NY": {
      "pc_providers": 1963,
      "rural_pct": 12,
      "racial_gap": 3.4,
      "wr": "none"
    },
    "OK": {
      "pc_providers": 534,
      "rural_pct": 35,
      "racial_gap": 4.3,
      "wr": "pending"
    }
  },
  "median_rural_pct": 25.0,
  "median_pc_providers": 935.5
}